tealc/__init__.py
tealc/__main__.py
tealc/cli.py
tealc/frequency_chart.json
tealc/manual.txt
tealc/material_codes.json
tealc/tealc.py
tealc/tension_models.json
tealc/unit_weights.json
tealc-0.2.0.dist-info/LICENSE.txt
tealc-0.2.0.dist-info/METADATA
tealc-0.2.0.dist-info/WHEEL
tealc-0.2.0.dist-info/entry_points.txt
tealc-0.2.0.dist-info/top_level.txt
tealc-0.2.0.dist-info/RECORD
