Metadata-Version: 2.1
Name: tealc
Version: 0.2.0
Summary: Tension Estimate cALCulator for stringed instruments.
Home-page: https://github.com/davidelambert/tealc
Author: David E. Lambert
Author-email: david@davidelambert.com
License: MIT
Project-URL: Bug Reporting, https://github.com/davidelambert/tealc/issues
Platform: UNKNOWN
Classifier: License :: OSI Approved :: MIT License
Classifier: Development Status :: 4 - Beta
Classifier: Programming Language :: Python
Classifier: Programming Language :: Python :: 3
Classifier: Programming Language :: Python :: 3.7
Classifier: Programming Language :: Python :: 3.8
Classifier: Programming Language :: Python :: 3.9
Classifier: Programming Language :: Python :: 3.10
Classifier: Operating System :: POSIX :: Linux
Classifier: Operating System :: Microsoft :: Windows :: Windows 10
Classifier: Topic :: Utilities
Requires-Python: >=3.7
License-File: LICENSE.txt
Requires-Dist: Click
